[
{"title": "Hostile Takeover", "author": ["Franklin Horton"], "length": "Length: 8 hrs and 41 mins"},
{"title": "White Wolf", "author": ["John Conroe"], "length": "Length: 17 hrs and 38 mins"},
{"title": "Alpha", "author": ["Aleron Kong"], "length": "Length: 14 hrs and 1 min"},
{"title": "Accidental Champion", "author": ["Todd Herzman"], "length": "Length: 20 hrs and 46 mins"},
{"title": "Rift in the Soul", "author": ["Faith Hunter"], "length": "Length: 15 hrs and 21 mins"},
{"title": "So This Is War", "author": ["Meghan Quinn"], "length": "Length: 13 hrs and 45 mins"},
{"title": "Practical Adept", "author": ["Terry Mancour"], "length": "Length: 32 hrs and 57 mins"},
{"title": "The Primal Hunter 9: A LitRPG Adventure", "author": ["Zogarth"], "length": "Length: 20 hrs and 23 mins"},
{"title": "Scythe & Sparrow", "author": ["Brynne Weaver"], "length": "Length: Not Yet Known"},
{"title": "Sanctuary", "author": ["Ilona Andrews"], "length": "Length: Not Yet Known"},
{"title": "Nobody Like Us", "author": ["Krista Ritchie", "Becca Ritchie"], "length": "Length: 25 hrs and 21 mins"},
{"title": "The Edges of Power", "author": ["Alexey Osadchuk", "Zachary J. Lorang - translated by"], "length": "Length: 9 hrs and 11 mins"},
{"title": "Chaos", "author": ["Luna Mason"], "length": "Length: 10 hrs and 9 mins"},
{"title": "Protocols", "author": ["Andrew Huberman"], "length": "Length: Not Yet Known"},
{"title": "Murder at an English Séance", "author": ["Jessica Ellicott"], "length": "Length: 9 hrs and 30 mins"},
{"title": "Murder at the Rusty Anchor", "author": ["Maddie Day"], "length": "Length: 7 hrs and 1 min"},
{"title": "Defiance of the Fall 13", "author": ["TheFirstDefier", "JF Brink"], "length": "Length: 24 hrs and 35 mins"},
{"title": "Aether", "author": ["Molly J. Bragg"], "length": "Length: 10 hrs and 23 mins"},
{"title": "Magic Rises (Dramatized Adaptation)", "author": ["Ilona Andrews"], "length": "Length: 11 hrs"},
{"title": "Lost", "author": ["John G. Hartness"], "length": "Length: 8 hrs and 36 mins"},
{"title": "Ascension", "author": ["Kerberos"], "length": "Length: 9 hrs and 37 mins"},
{"title": "Filthy Rich Fae", "author": ["Geneva Lee"], "length": "Length: 14 hrs and 27 mins"},
{"title": "Paw-ful Premonition", "author": ["Danielle Garrett"], "length": "Length: 5 hrs and 58 mins"},
{"title": "Junkyard Roadhouse", "author": ["Faith Hunter"], "length": "Length: 4 hrs and 36 mins"},
{"title": "Democracy or Else", "author": ["Jon Favreau", "Jon Lovett", "Tommy Vietor", "Josh Halloway"], "length": "Length: 3 hrs and 15 mins"},
{"title": "Houseswap 101", "author": ["Jaime Clevenger"], "length": "Length: 8 hrs and 39 mins"},
{"title": "He Who Fights with Monsters 11: A LitRPG Adventure", "author": ["Shirtaloon", "Travis Deverell"], "length": "Length: 28 hrs and 36 mins"},
{"title": "Requiem for a Mouse", "author": ["Miranda James"], "length": "Length: 7 hrs and 42 mins"},
{"title": "Whispers of the Deep", "author": ["Emma Hamm"], "length": "Length: 10 hrs and 37 mins"},
{"title": "When the Night Comes Falling", "author": ["Howard Blum"], "length": "Length: 5 hrs and 43 mins"},
{"title": "Love Letters to a Serial Killer", "author": ["Tasha Coryell"], "length": "Length: 8 hrs and 59 mins"},
{"title": "Legend of the Arch Magus: Publisher's Pack 6", "author": ["Michael Sisa"], "length": "Length: 14 hrs and 26 mins"},
{"title": "Sovereign", "author": ["Raya Morris Edwards"], "length": "Length: 10 hrs and 49 mins"},
{"title": "The Hunter's Gambit", "author": ["Ciel Pierlot"], "length": "Length: 11 hrs and 16 mins"},
{"title": "Sunrise on the Reaping", "author": ["Suzanne Collins"], "length": "Length: Not Yet Known"},
{"title": "Children of Anguish and Anarchy", "author": ["Tomi Adeyemi"], "length": "Length: 10 hrs and 2 mins"},
{"title": "Indaria", "author": ["SunriseCV"], "length": "Length: 13 hrs and 57 mins"},
{"title": "Will Leave the Galaxy for Good", "author": ["Yahtzee Croshaw"], "length": "Length: 9 hrs and 50 mins"},
{"title": "Tangled Up in You", "author": ["Christina Lauren"], "length": "Length: 9 hrs and 56 mins"},
{"title": "Dawn of the Density God", "author": ["ToraAKR"], "length": "Length: 14 hrs and 42 mins"},
{"title": "World Undone", "author": ["Sarah Lyons Fleming"], "length": "Length: 14 hrs and 10 mins"},
{"title": "Murder at Traitors' Gate", "author": ["Irina Shapiro"], "length": "Length: 10 hrs and 46 mins"},
{"title": "Throne World", "author": ["B.V. Larson"], "length": "Length: 12 hrs and 29 mins"},
{"title": "Onyx Storm", "author": ["Rebecca Yarros"], "length": "Length: 14 hrs and 15 mins"},
{"title": "Slash or Pass", "author": ["Tylor Paige"], "length": "Length: 10 hrs and 27 mins"},
{"title": "Wigglesworth on the Anointing", "author": ["Smith Wigglesworth"], "length": "Length: 6 hrs and 6 mins"},
{"title": "Four Horsemen", "author": ["Michael Chatfield"], "length": "Length: 14 hrs and 3 mins"},
{"title": "Wildest Dreams", "author": ["Kristen Proby"], "length": "Length: Not Yet Known"},
{"title": "The Songbird and the Heart of Stone", "author": ["Carissa Broadbent"], "length": "Length: 15 hrs and 33 mins"},
{"title": "Protecting Remi", "author": ["Susan Stoker"], "length": "Length: 8 hrs and 51 mins"},
{"title": "Sylver Seeker 4", "author": ["Kennit Kenway"], "length": "Length: 20 hrs and 50 mins"},
{"title": "The Sinner", "author": ["Dannika Dark"], "length": "Length: 11 hrs and 4 mins"},
{"title": "Legend to Farmer 2", "author": ["Dante King"], "length": "Length: 8 hrs and 40 mins"},
{"title": "Iron Flame (Part 2 of 2) (Dramatized Adaptation)", "author": ["Rebecca Yarros"], "length": "Length: 11 hrs"},
{"title": "Overlord, Vol. 14", "author": ["Kugane Maruyama", "so-bin - illustrator", "Andrew Cunningham - translator"], "length": "Length: 10 hrs"},
{"title": "Protocols", "author": ["Andrew D. Huberman Ph.D."], "length": "Length: 10 hrs"},
{"title": "Twisted Lives", "author": ["Tim Tigner"], "length": "Length: 9 hrs and 56 mins"},
{"title": "The Red Book", "author": ["C. G. Jung", "Sonu Shamdasani - editor translator"], "length": "Length: 20 hrs and 16 mins"},
{"title": "Imminent", "author": ["Luis Elizondo"], "length": "Length: 12 hrs"},
{"title": "The Last Ship", "author": ["Nicholas Sansbury Smith"], "length": "Length: 12 hrs and 41 mins"},
{"title": "The Cycle of Galand", "author": ["Edward W. Robertson"], "length": "Length: 26 hrs and 49 mins"},
{"title": "You'll Never Find Me", "author": ["Allison Brennan"], "length": "Length: 10 hrs and 31 mins"},
{"title": "Apocalypse Redux, Book 6", "author": ["Jakob H. Greif"], "length": "Length: 16 hrs and 13 mins"},
{"title": "Nemesis", "author": ["Gregg Hurwitz"], "length": "Length: 15 hrs"},
{"title": "One Cursed Rose", "author": ["Rebecca Zanetti"], "length": "Length: 11 hrs and 42 mins"},
{"title": "Here One Moment", "author": ["Liane Moriarty"], "length": "Length: 18 hrs"},
{"title": "The House of Beckham", "author": ["Tom Bower"], "length": "Length: 14 hrs and 10 mins"},
{"title": "Monsters Mayhem & Misfits 4", "author": ["Jack Spry", "Marcus Sloss"], "length": "Length: 8 hrs and 24 mins"},
{"title": "The Healer's Way #4", "author": ["Oleg Sapphire", "Alexey Kovtunov", "Jennifer E. Sunseri - translator"], "length": "Length: 8 hrs and 41 mins"},
{"title": "Mark Me", "author": ["Mila Young"], "length": "Length: 11 hrs and 38 mins"},
{"title": "Bitter Waters", "author": ["Vivian Shaw"], "length": "Length: 4 hrs and 40 mins"},
{"title": "The Silurian Bridge", "author": ["Greig Beck"], "length": "Length: 14 hrs and 35 mins"},
{"title": "Wind and Truth", "author": ["Brandon Sanderson"], "length": "Length: 55 hrs"},
{"title": "The Hidden Falling", "author": ["Kelly Cove"], "length": "Length: 12 hrs and 21 mins"},
{"title": "Tax-Free Wealth", "author": ["Tom Wheelwright CPA", "Robert Kiyosaki - foreword"], "length": "Length: 8 hrs and 50 mins"},
{"title": "LastRock", "author": ["Phil Tucker"], "length": "Length: 26 hrs and 2 mins"},
{"title": "Everyone Knows but You", "author": ["Thomas E. Ricks"], "length": "Length: 6 hrs and 7 mins"},
{"title": "Colin", "author": ["Grae Bryan"], "length": "Length: 7 hrs and 33 mins"},
{"title": "Wayward Earth", "author": ["Jason Anspach", "J.N. Chaney"], "length": "Length: 12 hrs and 40 mins"},
{"title": "Cue the Sun!", "author": ["Emily Nussbaum"], "length": "Length: 15 hrs and 11 mins"},
{"title": "Incidents Around the House", "author": ["Josh Malerman"], "length": "Length: 8 hrs and 23 mins"},
{"title": "Path of the Berserker 2: A Daopocalypse Progression Fantasy", "author": ["Rick Scott"], "length": "Length: 23 hrs and 6 mins"},
{"title": "A Death in Cornwall", "author": ["Daniel Silva"], "length": "Length: 9 hrs and 24 mins"},
{"title": "A Novel Love Story", "author": ["Ashley Poston"], "length": "Length: 10 hrs and 56 mins"},
{"title": "Beware of Chicken 4: A Xianxia Cultivation Novel", "author": ["Casualfarmer"], "length": "Length: 30 hrs and 8 mins"},
{"title": "Tom Clancy Defense Protocol", "author": ["Brian Andrews", "Jeffrey Wilson"], "length": "Length: 15 hrs"},
{"title": "Red Elf Ranch", "author": ["Michael Dalton"], "length": "Length: 6 hrs and 36 mins"},
{"title": "All the Colors of the Dark", "author": ["Chris Whitaker"], "length": "Length: 14 hrs and 37 mins"},
{"title": "Emperor's End", "author": ["Kyle Kirrin"], "length": "Length: 16 hrs and 18 mins"},
{"title": "Tuesday", "author": ["Draith"], "length": "Length: 14 hrs and 23 mins"},
{"title": "Heretical Fishing 2: A Cozy Guide to Annoying the Cults, Outsmarting the Fish, and Alienating Oneself", "author": ["Haylock Jobson"], "length": "Length: 25 hrs and 4 mins"},
{"title": "Knot for a Moment", "author": ["Devyn Sinclair"], "length": "Length: 17 hrs and 30 mins"},
{"title": "Fall with Me", "author": ["Becka Mack"], "length": "Length: 16 hrs and 21 mins"},
{"title": "A Ruse of Shadows", "author": ["Sherry Thomas"], "length": "Length: 13 hrs and 3 mins"},
{"title": "Peg and Rose Play the Ponies", "author": ["Laurien Berenson"], "length": "Length: 9 hrs and 20 mins"},
{"title": "The Daughters' War", "author": ["Christopher Buehlman"], "length": "Length: 13 hrs and 14 mins"},
{"title": "You Are a Channel", "author": ["Sara Landon"], "length": "Length: 7 hrs and 16 mins"},
{"title": "The Big Empty", "author": ["Robert Crais"], "length": "Length: 15 hrs"},
{"title": "To Die For", "author": ["David Baldacci"], "length": "Length: 12 hrs"},
{"title": "Sentinel", "author": ["Mark Greaney"], "length": "Length: 13 hrs and 34 mins"},
{"title": "City of the Damned", "author": ["David Guymer"], "length": "Length: 12 hrs and 56 mins"},
{"title": "Ember", "author": ["Jeffrey Wilson", "Brian Andrews"], "length": "Length: 14 hrs"},
{"title": "Murder at Ashton Steeple", "author": ["Karen Baugh Menuhin"], "length": "Length: 8 hrs and 40 mins"},
{"title": "Resurrection", "author": ["Danielle Steel"], "length": "Length: 6 hrs and 59 mins"},
{"title": "The Garden Against Time", "author": ["Olivia Laing"], "length": "Length: 9 hrs and 17 mins"},
{"title": "The Legend of Randidly Ghosthound 8", "author": ["Noret Flood", "puddles4263"], "length": "Length: 29 hrs and 7 mins"},
{"title": "House of Sky and Breath (Part 1 of 2) (Dramatized Adaptation)", "author": ["Sarah J. Maas"], "length": "Length: 11 hrs"},
{"title": "Rune Seeker 3", "author": ["J.M. Clarke", "C.J. Thompson"], "length": "Length: 24 hrs and 24 mins"},
{"title": "What Would the Rockefellers Do?", "author": ["Garrett Gunderson", "Michael Isom"], "length": "Length: 4 hrs and 46 mins"},
{"title": "The Mirror", "author": ["Nora Roberts"], "length": "Length: 14 hrs and 24 mins"},
{"title": "Husbands & Lovers", "author": ["Beatriz Williams"], "length": "Length: 12 hrs and 31 mins"},
{"title": "Shanghai", "author": ["Joseph Kanon"], "length": "Length: 10 hrs and 24 mins"},
{"title": "Dreamer's Throne 3", "author": ["Seth Ring"], "length": "Length: 11 hrs and 50 mins"},
{"title": "All the Worst Humans", "author": ["Phil Elwood"], "length": "Length: 6 hrs and 42 mins"},
{"title": "Ask Not", "author": ["Maureen Callahan"], "length": "Length: 11 hrs and 18 mins"},
{"title": "Paved in Blood", "author": ["Sonja Grey"], "length": "Length: 10 hrs and 7 mins"},
{"title": "Learn Spanish with Popular Slang Words & Phrases", "author": ["Emily Montgomery"], "length": "Length: 11 hrs and 41 mins"},
{"title": "Undignified", "author": ["Deanna Lorea"], "length": "Length: 3 hrs and 22 mins"},
{"title": "Enemy A(n)t the Gates", "author": ["RinoZ"], "length": "Length: 20 hrs and 49 mins"},
{"title": "Pitch Dark", "author": ["Paul Doiron"], "length": "Length: 8 hrs and 22 mins"},
{"title": "Parenting Teens with Love & Logic", "author": ["Foster Cline", "Jim Fay"], "length": "Length: 10 hrs and 27 mins"},
{"title": "How the Light Gets In", "author": ["Joyce Maynard"], "length": "Length: 16 hrs and 38 mins"},
{"title": "Flashback", "author": ["Iris Johansen", "Roy Johansen"], "length": "Length: 8 hrs and 10 mins"},
{"title": "The Black Bird Oracle", "author": ["Deborah Harkness"], "length": "Length: 17 hrs and 4 mins"},
{"title": "Rise of the Weakest Summoner, Volume IX", "author": ["J.R. Saileri"], "length": "Length: 19 hrs"},
{"title": "Desolation", "author": ["Mark Morton", "Ben Opipari - contributor"], "length": "Length: 9 hrs and 2 mins"},
{"title": "Dire Straits and Entwined Fates", "author": ["Alice Winters"], "length": "Length: 10 hrs and 29 mins"},
{"title": "Echo of Worlds", "author": ["M. R. Carey"], "length": "Length: 16 hrs and 56 mins"},
{"title": "A Great Disorder", "author": ["Richard Slotkin"], "length": "Length: 20 hrs and 53 mins"},
{"title": "The Singularity Is Nearer", "author": ["Ray Kurzweil"], "length": "Length: 10 hrs and 25 mins"},
{"title": "Effective Psychotherapists", "author": ["William R. Miller PhD", "Theresa B. Moyers PhD"], "length": "Length: 6 hrs and 2 mins"},
{"title": "Bear", "author": ["Julia Phillips"], "length": "Length: 7 hrs and 51 mins"},
{"title": "Dungeon Cataclysm", "author": ["Playwars aka Alex S. Weber"], "length": "Length: 12 hrs"},
{"title": "We Who Wrestle with God", "author": ["Jordan B. Peterson"], "length": "Length: 13 hrs"},
{"title": "Viper", "author": ["Suzanne Wright"], "length": "Length: 10 hrs"},
{"title": "The Legend of Randidly Ghosthound 7", "author": ["Noret Flood", "puddles4263"], "length": "Length: 27 hrs and 53 mins"},
{"title": "Voracious", "author": ["James T. Callum"], "length": "Length: 16 hrs and 34 mins"},
{"title": "Hell Divers XII: Heroes", "author": ["Nicholas Sansbury Smith"], "length": "Length: 13 hrs and 30 mins"},
{"title": "Parenting with Love & Logic", "author": ["Foster Cline", "Jim Fay"], "length": "Length: 9 hrs and 24 mins"},
{"title": "Don't Let the Devil Ride", "author": ["Ace Atkins"], "length": "Length: 14 hrs and 42 mins"},
{"title": "Forsaken Relic", "author": ["Caroline Peckham", "Susanne Valenti"], "length": "Length: 10 hrs and 14 mins"},
{"title": "Investing for Teenagers Made Simple", "author": ["Riley Wealth"], "length": "Length: 3 hrs and 40 mins"},
{"title": "The Burning Rooms", "author": ["Anni Taylor"], "length": "Length: 11 hrs and 54 mins"},
{"title": "Pieces of Us", "author": ["T. B. Markinson", "Miranda MacLeod"], "length": "Length: 10 hrs and 14 mins"},
{"title": "Tress of the Emerald Sea", "author": ["Brandon Sanderson"], "length": "Length: 12 hrs and 27 mins"},
{"title": "Finding Mr. Write", "author": ["Kelley Armstrong"], "length": "Length: 10 hrs and 27 mins"},
{"title": "Framed", "author": ["John Grisham", "Jim McCloskey"], "length": "Length: 12 hrs"},
{"title": "Burn", "author": ["Anna Hackett"], "length": "Length: 5 hrs and 36 mins"},
{"title": "Soulbound 3: A Haremlit Fantasy Adventure", "author": ["Cassius Lange"], "length": "Length: 11 hrs and 2 mins"},
{"title": "Blood for Power 2", "author": ["Scott W. James"], "length": "Length: 10 hrs and 29 mins"},
{"title": "Safe for Now", "author": ["Bob Howard"], "length": "Length: 12 hrs and 55 mins"},
{"title": "Now or Never", "author": ["Janet Evanovich"], "length": "Length: 8 hrs"},
{"title": "Passions in Death: An Eve Dallas Novel", "author": ["J. D. Robb"], "length": "Length: 13 hrs and 54 mins"},
{"title": "Whispers in the Dark", "author": ["Nikole Knight", "Lily Mayne"], "length": "Length: 10 hrs and 24 mins"},
{"title": "The Year of What If", "author": ["Phaedra Patrick"], "length": "Length: 9 hrs and 3 mins"},
{"title": "Collapse", "author": ["Sean Oswald"], "length": "Length: 12 hrs and 51 mins"},
{"title": "The Amethyst Kingdom", "author": ["A.K. Mulford"], "length": "Length: 13 hrs and 23 mins"},
{"title": "The Song Rising", "author": ["Samantha Shannon"], "length": "Length: 13 hrs and 12 mins"},
{"title": "Charming Deception", "author": ["Jaine Diamond"], "length": "Length: 13 hrs and 36 mins"},
{"title": "A Scion's Duty", "author": ["Tom Elliot"], "length": "Length: 16 hrs and 43 mins"},
{"title": "The Mist Thief", "author": ["LJ Andrews"], "length": "Length: 14 hrs and 6 mins"},
{"title": "The Knight", "author": ["Will Wight"], "length": "Length: 9 hrs and 48 mins"},
{"title": "Brave New You", "author": ["Cory Allen"], "length": "Length: 6 hrs and 28 mins"},
{"title": "Not Just Gal Pals", "author": ["Elizabeth Luly"], "length": "Length: 7 hrs and 15 mins"},
{"title": "My Darling Dreadful Thing", "author": ["Johanna van Veen"], "length": "Length: 9 hrs and 58 mins"},
{"title": "Heavy Is the Crown", "author": ["J.N. Chaney", "Terry Maggert"], "length": "Length: 10 hrs and 5 mins"},
{"title": "Wolves of the Wastes", "author": ["D.E. Sherman"], "length": "Length: 18 hrs and 19 mins"},
{"title": "Mean Spirited", "author": ["Nick Roberts", "Crystal Lake Publishing", "Crystal Lake Audio"], "length": "Length: 10 hrs and 9 mins"},
{"title": "A Happier Life", "author": ["Kristy Woodson Harvey"], "length": "Length: 12 hrs and 9 mins"},
{"title": "Becoming Earth", "author": ["Ferris Jabr"], "length": "Length: 9 hrs and 27 mins"},
{"title": "Secrets and Strife: An Isekai LitRPG", "author": ["SourpatchHero"], "length": "Length: 18 hrs and 53 mins"},
{"title": "Summer Romance", "author": ["Annabel Monaghan"], "length": "Length: 8 hrs and 27 mins"},
{"title": "Brie Careful What You Wish For", "author": ["Linda Reilly"], "length": "Length: 8 hrs and 49 mins"},
{"title": "Source Code", "author": ["Bill Gates"], "length": "Length: 11 hrs"},
{"title": "Life as No One Knows It", "author": ["Sara Imari Walker"], "length": "Length: 8 hrs"},
{"title": "Somewhere Beyond the Sea", "author": ["TJ Klune"], "length": "Length: 12 hrs"},
{"title": "Dead Country", "author": ["Max Gladstone"], "length": "Length: 8 hrs and 57 mins"},
{"title": "Internal Family Systems Skills Training Manual", "author": ["Frank Anderson", "Richard C. Schwartz"], "length": "Length: 5 hrs and 55 mins"},
{"title": "Reckless", "author": ["Lauren Roberts"], "length": "Length: 11 hrs"},
{"title": "Darkest Night", "author": ["Alessa Thorn"], "length": "Length: 6 hrs and 49 mins"},
{"title": "In Too Deep", "author": ["Lee Child", "Andrew Child"], "length": "Length: 10 hrs"},
{"title": "Competitive Strategy", "author": ["Michael E. Porter"], "length": "Length: 15 hrs and 31 mins"},
{"title": "Moral Injuries", "author": ["Christie Watson"], "length": "Length: 9 hrs and 42 mins"},
{"title": "8-Week Couples Relationship Therapy Workbook", "author": ["Taylor Blake"], "length": "Length: 3 hrs and 16 mins"},
{"title": "The Hookup Mix-Up", "author": ["Riley Hart"], "length": "Length: 6 hrs and 47 mins"},
{"title": "Forgotten Desires", "author": ["Corinne Michaels"], "length": "Length: 9 hrs and 8 mins"},
{"title": "Fragile Sanctuary", "author": ["Catherine Cowles"], "length": "Length: 11 hrs and 32 mins"},
{"title": "Learn Spanish for Beginners: +20H Bundle", "author": ["Emily Montgomery"], "length": "Length: 23 hrs and 17 mins"},
{"title": "Sour Candy", "author": ["Kealan Patrick Burke"], "length": "Length: 2 hrs and 36 mins"},
{"title": "Horror Movie", "author": ["Paul Tremblay"], "length": "Length: 7 hrs and 23 mins"},
{"title": "Capture or Kill", "author": ["Vince Flynn", "Don Bentley"], "length": "Length: 12 hrs"},
{"title": "Quantum Conjurations", "author": ["Kevin McLaughlin", "Michael Anderle"], "length": "Length: 7 hrs and 33 mins"},
{"title": "The Dirty Ones", "author": ["JA Huss"], "length": "Length: 9 hrs and 6 mins"},
{"title": "Tom Clancy Shadow State", "author": ["M.P. Woodward"], "length": "Length: 15 hrs"},
{"title": "The Angry Land", "author": ["William W. Johnstone", "J. A. Johnstone"], "length": "Length: 9 hrs and 7 mins"},
{"title": "All the Dust That Falls 3", "author": ["zaifyr"], "length": "Length: 19 hrs and 7 mins"},
{"title": "How to Stop Breaking Your Own Heart", "author": ["Meggan Roxanne"], "length": "Length: 5 hrs and 15 mins"},
{"title": "You Like It Darker", "author": ["Stephen King"], "length": "Length: 20 hrs and 12 mins"},
{"title": "The Rest Is History", "author": ["Sara Madderson"], "length": "Length: 9 hrs and 46 mins"},
{"title": "At the Edge of Empire", "author": ["Edward Wong"], "length": "Length: 16 hrs and 49 mins"},
{"title": "Craving Chaos", "author": ["Jill Ramsower"], "length": "Length: 8 hrs and 32 mins"},
{"title": "Capture, Evolve, Survive: Book 1", "author": ["Dante King"], "length": "Length: 10 hrs and 8 mins"},
{"title": "All the Skills 4: A Deck-Building LitRPG", "author": ["Honour Rae"], "length": "Length: 14 hrs and 26 mins"},
{"title": "Dance of the Forest King", "author": ["Alessa Thorn"], "length": "Length: 5 hrs and 49 mins"},
{"title": "Kingdom of Claw", "author": ["Demi Winters"], "length": "Length: 24 hrs and 47 mins"},
{"title": "Look on the Bright Side", "author": ["Kristan Higgins"], "length": "Length: 12 hrs and 34 mins"},
{"title": "The Witch of Webs", "author": ["pirateaba"], "length": "Length: 45 hrs and 53 mins"},
{"title": "Under Locke", "author": ["Mariana Zapata"], "length": "Length: 15 hrs and 38 mins"},
{"title": "The Alpha's Protective Mate", "author": ["Jaymin Snow"], "length": "Length: 12 hrs and 41 mins"},
{"title": "A Stealthy Situation", "author": ["Saxon James"], "length": "Length: 6 hrs and 47 mins"},
{"title": "The Ballad of Smallhope and Pennyroyal", "author": ["Jodi Taylor"], "length": "Length: 10 hrs"},
{"title": "The Waiting", "author": ["Michael Connelly"], "length": "Length: 12 hrs"},
{"title": "The Worst of You", "author": ["Sarah Richards"], "length": "Length: 10 hrs and 51 mins"},
{"title": "Batting Style", "author": ["Louisa Masters"], "length": "Length: 6 hrs and 49 mins"},
{"title": "Broken Warrior", "author": ["K.C. Wells", "Parker Williams"], "length": "Length: 9 hrs and 51 mins"},
{"title": "Harmony Island Gazette", "author": ["Anne-Marie Meyer"], "length": "Length: 8 hrs and 1 min"},
{"title": "Bronze Rank Brewer", "author": ["James Ghoul"], "length": "Length: 21 hrs and 52 mins"},
{"title": "Red Sky Mourning", "author": ["Jack Carr"], "length": "Length: 15 hrs and 28 mins"},
{"title": "Life of a Freelancer 2", "author": ["G.S. D'Moore"], "length": "Length: 19 hrs and 55 mins"},
{"title": "Encore", "author": ["Helen Hardt"], "length": "Length: 7 hrs and 51 mins"},
{"title": "Forged in Frost", "author": ["Jasmine Walt"], "length": "Length: 10 hrs and 53 mins"},
{"title": "Under the Breaking Sky: The Complete Apocalyptic Horror Series", "author": ["Nick Clausen"], "length": "Length: 59 hrs and 36 mins"},
{"title": "All the Kings Men", "author": ["Maggie McAllister"], "length": "Length: 1 hr and 14 mins"},
{"title": "My Choice Is You", "author": ["Mel Dau"], "length": "Length: 5 hrs and 59 mins"},
{"title": "Children of Dune", "author": ["Frank Herbert"], "length": "Length: 16 hrs and 51 mins"},
{"title": "Uncertain", "author": ["Maggie Jackson"], "length": "Length: 10 hrs and 46 mins"},
{"title": "True Believer", "author": ["Jack Carr"], "length": "Length: 15 hrs and 44 mins"},
{"title": "Forbidden King", "author": ["Laura Pavlov"], "length": "Length: 9 hrs and 6 mins"},
{"title": "Born of Blood and Ash", "author": ["Jennifer L. Armentrout"], "length": "Length: 24 hrs"},
{"title": "A Storm of Swords", "author": ["George R.R. Martin"], "length": "Length: 47 hrs and 34 mins"},
{"title": "Seabreeze Gala", "author": ["Jan Moran"], "length": "Length: 6 hrs and 42 mins"},
{"title": "House of Sky and Breath", "author": ["Sarah J. Maas"], "length": "Length: 27 hrs and 42 mins"},
{"title": "Our Little Secret", "author": ["Lisa Jackson"], "length": "Length: 13 hrs and 34 mins"},
{"title": "Death at the Sign of the Rook", "author": ["Kate Atkinson"], "length": "Length: 12 hrs"},
{"title": "The Power of Your Dreams", "author": ["Stephanie Ike Okafor", "Touré Roberts"], "length": "Length: 7 hrs"},
{"title": "After the Flying Saucers Came", "author": ["Greg Eghigian"], "length": "Length: 15 hrs and 49 mins"},
{"title": "Change of Heart", "author": ["Kate Canterbary"], "length": "Length: 10 hrs and 51 mins"},
{"title": "The Misfit Mage and His Dashing Devil", "author": ["MN Bennet"], "length": "Length: 11 hrs and 16 mins"},
{"title": "Still Trappin' Through the Snow", "author": ["BriAnn Danae"], "length": "Length: 7 hrs and 38 mins"},
{"title": "Knot Guaranteed", "author": ["Jillian West"], "length": "Length: 9 hrs and 37 mins"},
{"title": "Siege of Vraks", "author": ["Steve Lyons"], "length": "Length: 9 hrs and 48 mins"},
{"title": "The Adversary", "author": ["Torsten Weitze", "Tim Casey - translator"], "length": "Length: 22 hrs and 44 mins"},
{"title": "Addicted to the Ruin", "author": ["Rosa Lee"], "length": "Length: 9 hrs and 10 mins"},
{"title": "Devil's Own", "author": ["K.M. Neuhold"], "length": "Length: 9 hrs and 15 mins"},
{"title": "Sidewinder", "author": ["L.T. Ryan", "Brian Shea"], "length": "Length: 5 hrs and 36 mins"},
{"title": "The Forever Ship", "author": ["Scott Bartlett", "Joshua James"], "length": "Length: 18 hrs and 20 mins"},
{"title": "A Clash of Kings", "author": ["George R.R. Martin"], "length": "Length: 37 hrs and 12 mins"},
{"title": "Autocracy, Inc.", "author": ["Anne Applebaum"], "length": "Length: 4 hrs and 48 mins"},
{"title": "Dune Messiah", "author": ["Frank Herbert"], "length": "Length: 8 hrs and 57 mins"},
{"title": "The Other Passenger", "author": ["JE Rowney"], "length": "Length: 5 hrs and 23 mins"},
{"title": "Beyond the Badge: Nox", "author": ["Jeanne St. James"], "length": "Length: 11 hrs and 31 mins"},
{"title": "All the Little Raindrops", "author": ["Mia Sheridan"], "length": "Length: 13 hrs and 51 mins"},
{"title": "Princes of Carnage", "author": ["Eva Ashwood"], "length": "Length: 14 hrs and 16 mins"},
{"title": "Words of Radiance", "author": ["Brandon Sanderson"], "length": "Length: 48 hrs and 13 mins"},
{"title": "Zenith", "author": ["Jonathan Yanez", "Ross Buzzell"], "length": "Length: 12 hrs and 28 mins"},
{"title": "Just for the Summer", "author": ["Abby Jimenez"], "length": "Length: 11 hrs and 43 mins"},
{"title": "A Calamity of Souls", "author": ["David Baldacci"], "length": "Length: 14 hrs and 28 mins"},
{"title": "God of War", "author": ["Rina Kent"], "length": "Length: 15 hrs"},
{"title": "The Rule of Five Seconds", "author": ["Clark Hoshino"], "length": "Length: 4 hrs and 13 mins"},
{"title": "Harry Potter and the Goblet of Fire (Narrated by Stephen Fry)", "author": ["J.K. Rowling"], "length": "Length: 20 hrs and 54 mins"},
{"title": "The Girl in the Dark", "author": ["A.J. Rivers"], "length": "Length: 7 hrs and 20 mins"},
{"title": "Going Home", "author": ["Brad Dennison"], "length": "Length: 8 hrs and 28 mins"},
{"title": "Crown of Midnight", "author": ["Sarah J. Maas"], "length": "Length: 12 hrs and 43 mins"},
{"title": "Shadow of Doubt", "author": ["Brad Thor"], "length": "Length: 11 hrs and 30 mins"},
{"title": "A Daughter of Fair Verona", "author": ["Christina Dodd"], "length": "Length: 8 hrs and 23 mins"},
{"title": "Harry Potter and the Goblet of Fire, Book 4", "author": ["J.K. Rowling"], "length": "Length: 20 hrs and 36 mins"},
{"title": "I Who Have Never Known Men", "author": ["Jacqueline Harpman"], "length": "Length: 6 hrs and 10 mins"},
{"title": "When You Smile", "author": ["Melissa Brayden"], "length": "Length: 10 hrs and 56 mins"},
{"title": "Market for Murder", "author": ["Heather Graham"], "length": "Length: 9 hrs and 4 mins"},
{"title": "Breaking the Habit of Being Yourself", "author": ["Joe Dispenza"], "length": "Length: 10 hrs and 49 mins"},
{"title": "Love Unwritten", "author": ["Lauren Asher"], "length": "Length: 14 hrs and 28 mins"},
{"title": "Storm of Secrets and Sorrow", "author": ["Melissa Roehrich"], "length": "Length: 23 hrs and 41 mins"},
{"title": "A Billionaire's Weakness 2", "author": ["Londyn Lenz"], "length": "Length: 9 hrs and 56 mins"},
{"title": "Play Dead", "author": ["Annabel Chase"], "length": "Length: 8 hrs and 30 mins"},
{"title": "The Mercy of Gods", "author": ["James S.A. Corey"], "length": "Length: 18 hrs and 30 mins"},
{"title": "Heir of Fire", "author": ["Sarah J. Maas"], "length": "Length: 17 hrs and 56 mins"},
{"title": "God Emperor of Dune", "author": ["Frank Herbert"], "length": "Length: 15 hrs and 48 mins"},
{"title": "I Never Knew Myself", "author": ["Melanie Rachel"], "length": "Length: 13 hrs and 42 mins"},
{"title": "Oathbringer", "author": ["Brandon Sanderson"], "length": "Length: 55 hrs and 5 mins"},
{"title": "Harry Potter and the Prisoner of Azkaban (Narrated by Stephen Fry)", "author": ["J.K. Rowling"], "length": "Length: 12 hrs and 3 mins"},
{"title": "Mind Games", "author": ["Nora Roberts"], "length": "Length: 14 hrs and 52 mins"},
{"title": "48 Laws of Power", "author": ["Robert Greene"], "length": "Length: 23 hrs and 6 mins"},
{"title": "The Laws of Human Nature", "author": ["Robert Greene"], "length": "Length: 28 hrs and 26 mins"},
{"title": "12 Rules for Life", "author": ["Jordan B. Peterson", "Norman Doidge MD"], "length": "Length: 15 hrs and 40 mins"},
{"title": "Target Omega", "author": ["Peter Kirsanow"], "length": "Length: 13 hrs and 24 mins"},
{"title": "The King's Ransom", "author": ["Janet Evanovich"], "length": "Length: 7 hrs and 30 mins"},
{"title": "The Power of Positive Faith with Bonus Book The Greatest Thing in the World (Original Classic Edition)", "author": ["Norman Vincent Peale", "Smiley Blanton", "Henry Drummond"], "length": "Length: 7 hrs and 39 mins"},
{"title": "Rhythm of War", "author": ["Brandon Sanderson"], "length": "Length: 57 hrs and 26 mins"},
{"title": "Empire of Storms", "author": ["Sarah J. Maas"], "length": "Length: 25 hrs and 18 mins"},
{"title": "A Court of Thorns and Roses", "author": ["Sarah J. Maas"], "length": "Length: 16 hrs and 7 mins"},
{"title": "Digital Marketing for Beginners: 2 Books in 1", "author": ["Ethan Robinson"], "length": "Length: 10 hrs and 46 mins"},
{"title": "Red Tithe", "author": ["Robbie MacNiven"], "length": "Length: 9 hrs and 48 mins"},
{"title": "Arrowood", "author": ["Laura McHugh"], "length": "Length: 10 hrs and 18 mins"},
{"title": "PMP PMBOK 7 Project Management Professional Audio Study Guide 2024-2025: Perfect for Commuting, Exercising, and doing Chores!", "author": ["Samuel Davidson", "Rebecca Davidson"], "length": "Length: 10 hrs"},
{"title": "Kingdom of Ash", "author": ["Sarah J. Maas"], "length": "Length: 33 hrs and 11 mins"},
{"title": "A Court of Frost and Starlight", "author": ["Sarah J. Maas"], "length": "Length: 6 hrs and 23 mins"},
{"title": "Camino Ghosts", "author": ["John Grisham"], "length": "Length: 10 hrs and 17 mins"},
{"title": "Avatar", "author": ["Seth Ring"], "length": "Length: 13 hrs and 30 mins"},
{"title": "When My Time Comes", "author": ["Diane Rehm", "John Grisham - foreword"], "length": "Length: 7 hrs and 34 mins"},
{"title": "The Dungeon Anarchist's Cookbook", "author": ["Matt Dinniman"], "length": "Length: 16 hrs and 54 mins"},
{"title": "The Hero of Ages", "author": ["Brandon Sanderson"], "length": "Length: 27 hrs and 25 mins"},
{"title": "He Who Fights with Monsters: A LitRPG Adventure", "author": ["Shirtaloon", "Travis Deverell"], "length": "Length: 28 hrs and 56 mins"},
{"title": "Frostbite", "author": ["Nicola Twilley"], "length": "Length: 12 hrs and 18 mins"},
{"title": "Do I Know You?", "author": ["Sadie Dingfelder"], "length": "Length: 7 hrs and 26 mins"},
{"title": "You Are a King", "author": ["Dr. Myles Munroe"], "length": "Length: 3 hrs and 57 mins"},
{"title": "It's Been a Pleasure, Noni Blake", "author": ["Claire Christian"], "length": "Length: 10 hrs and 26 mins"},
{"title": "La generación ansiosa", "author": ["Jonathan Haidt", "Verónica Puertollano López - traductor"], "length": "Length: 10 hrs and 50 mins"},
{"title": "Reborn as a Space Mercenary", "author": ["Ryuto"], "length": "Length: 6 hrs and 22 mins"},
{"title": "Never Date Your Brother's Best Friend", "author": ["Jules Barnard"], "length": "Length: 8 hrs and 20 mins"},
{"title": "An Aura of Mystery", "author": ["Joy Ellis"], "length": "Length: 12 hrs and 21 mins"},
{"title": "The Finish Line", "author": ["Kate Stewart"], "length": "Length: 14 hrs and 39 mins"},
{"title": "Fairy Tale", "author": ["Stephen King"], "length": "Length: 24 hrs and 6 mins"},
{"title": "Lights, Camera, Bones", "author": ["Carolyn Haines"], "length": "Length: 10 hrs and 34 mins"},
{"title": "Queen of Shadows", "author": ["Sarah J. Maas"], "length": "Length: 20 hrs and 43 mins"},
{"title": "Queen of Chaos", "author": ["Amelia Hutchins"], "length": "Length: 13 hrs and 50 mins"},
{"title": "The Impactful Vegan", "author": ["Robert Cheeke"], "length": "Length: 8 hrs and 48 mins"},
{"title": "The Chronicles of Narnia Complete Audio Collection", "author": ["C. S. Lewis"], "length": "Length: 33 hrs and 45 mins"},
{"title": "The Perfect Fit", "author": ["Sadie Kincaid"], "length": "Length: 10 hrs and 28 mins"},
{"title": "A Court of Silver Flames", "author": ["Sarah J. Maas"], "length": "Length: 26 hrs and 5 mins"},
{"title": "Mythos University: Book 2", "author": ["Alan Moria"], "length": "Length: 12 hrs and 36 mins"},
{"title": "Her Mafia Bride", "author": ["Persephone Black"], "length": "Length: 6 hrs and 59 mins"},
{"title": "House of Earth and Blood", "author": ["Sarah J. Maas"], "length": "Length: 27 hrs and 50 mins"},
{"title": "Harry Potter and the Sorcerer's Stone, Book 1", "author": ["J.K. Rowling"], "length": "Length: 8 hrs and 18 mins"},
{"title": "Curvy Girl Summer", "author": ["Danielle Allen"], "length": "Length: 12 hrs and 23 mins"},
{"title": "The Reckoning", "author": ["Caroline Peckham", "Susanne Valenti"], "length": "Length: 17 hrs and 40 mins"},
{"title": "A People's History of the United States", "author": ["Howard Zinn"], "length": "Length: 34 hrs and 8 mins"},
{"title": "He Who Fights with Monsters 5", "author": ["Shirtaloon", "Travis Deverell"], "length": "Length: 20 hrs and 5 mins"},
{"title": "He Who Fights with Monsters 9", "author": ["Shirtaloon", "Travis Deverell"], "length": "Length: 28 hrs and 3 mins"},
{"title": "The Stand", "author": ["Stephen King"], "length": "Length: 47 hrs and 47 mins"},
{"title": "A Court of Wings and Ruin", "author": ["Sarah J. Maas"], "length": "Length: 25 hrs and 9 mins"},
{"title": "Never Kiss a Fae", "author": ["Lexi C. Foss", "J.R. Thorn"], "length": "Length: 33 hrs and 10 mins"},
{"title": "The Rule Book", "author": ["Jennifer Blackwood"], "length": "Length: 9 hrs and 15 mins"},
{"title": "Wild with Happy", "author": ["Colman Domingo"], "length": "Length: 1 hr and 32 mins"},
{"title": "Dark Witch: Entangled Fates", "author": ["I. T. Lucas"], "length": "Length: 9 hrs and 32 mins"},
{"title": "A Court of Mist and Fury", "author": ["Sarah J. Maas"], "length": "Length: 23 hrs and 16 mins"},
{"title": "The Teacher", "author": ["Freida McFadden"], "length": "Length: 9 hrs and 35 mins"},
{"title": "Introduction to Cognitive Science", "author": ["Thad A. Polk", "The Great Courses"], "length": "Length: 12 hrs and 53 mins"},
{"title": "Ascendant King", "author": ["Kai Butler"], "length": "Length: 13 hrs and 21 mins"},
{"title": "Come What May", "author": ["A. M. Arthur"], "length": "Length: 8 hrs"},
{"title": "Soil Science for Beginners", "author": ["Dylan Grant"], "length": "Length: 5 hrs and 25 mins"},
{"title": "The Accidental Dating Experiment", "author": ["Lauren Blakely"], "length": "Length: 6 hrs and 55 mins"},
{"title": "A Court of Frost and Starlight (Dramatized Adaptation)", "author": ["Sarah J. Maas"], "length": "Length: 5 hrs and 33 mins"},
{"title": "Twisted Love", "author": ["Ana Huang"], "length": "Length: 10 hrs and 41 mins"},
{"title": "Redeeming Your Time", "author": ["Jordan Raynor"], "length": "Length: 6 hrs and 54 mins"},
{"title": "Carl's Doomsday Scenario", "author": ["Matt Dinniman"], "length": "Length: 11 hrs and 28 mins"},
{"title": "Harry Potter and the Chamber of Secrets (Narrated by Stephen Fry)", "author": ["J.K. Rowling"], "length": "Length: 9 hrs and 43 mins"},
{"title": "The Well of Ascension", "author": ["Brandon Sanderson"], "length": "Length: 28 hrs and 56 mins"},
{"title": "Funny Story", "author": ["Emily Henry"], "length": "Length: 11 hrs and 23 mins"},
{"title": "The Sunlit Man", "author": ["Brandon Sanderson"], "length": "Length: 11 hrs and 11 mins"},
{"title": "101 Essays That Will Change the Way You Think", "author": ["Brianna Wiest"], "length": "Length: 10 hrs and 45 mins"},
{"title": "SLAY (The Man in Gray Book 1)", "author": ["Scott Sigler", "Rob Otto"], "length": "Length: 13 hrs and 27 mins"},
{"title": "Never Finished", "author": ["David Goggins"], "length": "Length: 11 hrs and 6 mins"},
{"title": "Yumi and the Nightmare Painter", "author": ["Brandon Sanderson"], "length": "Length: 14 hrs and 43 mins"},
{"title": "The Wise Man's Fear", "author": ["Patrick Rothfuss"], "length": "Length: 42 hrs and 55 mins"},
{"title": "The Demon of Unrest", "author": ["Erik Larson"], "length": "Length: 17 hrs and 18 mins"},
{"title": "Tom Clancy Act of Defiance", "author": ["Brian Andrews", "Jeffrey Wilson"], "length": "Length: 17 hrs and 1 min"},
{"title": "Nexus", "author": ["Yuval Noah Harari"], "length": "Length: 14 hrs"},
{"title": "Morning Star (2 of 2) (Dramatized Adaptation)", "author": ["Pierce Brown"], "length": "Length: 10 hrs and 29 mins"},
{"title": "The Word of Promise Audio Bible—New King James Version, NKJV: Complete Bible", "author": ["Thomas Nelson Inc."], "length": "Length: 98 hrs and 1 min"},
{"title": "I Can't Even", "author": ["Lani Lynn Vale"], "length": "Length: 6 hrs and 26 mins"},
{"title": "Hercule Poirot: The Complete Short Stories", "author": ["Agatha Christie"], "length": "Length: 35 hrs and 5 mins"},
{"title": "Helping Children with ADHD and Oppositional Defiant Disorder", "author": ["SpreadLife Publishing"], "length": "Length: 8 hrs and 44 mins"},
{"title": "A Kingdom of Flesh and Fire", "author": ["Jennifer L. Armentrout"], "length": "Length: 24 hrs and 21 mins"},
{"title": "America Betrayed", "author": ["David Horowitz"], "length": "Length: 3 hrs and 9 mins"},
{"title": "Harry Potter and the Order of the Phoenix (Narrated by Stephen Fry)", "author": ["J.K. Rowling"], "length": "Length: 29 hrs and 1 min"},
{"title": "Alpha Theo", "author": ["C.J. Primer"], "length": "Length: 12 hrs and 4 mins"},
{"title": "Three Worlds", "author": ["Avi Shlaim"], "length": "Length: 11 hrs and 54 mins"},
{"title": "Honey", "author": ["Isabel Banta"], "length": "Length: 9 hrs and 12 mins"},
{"title": "The Duke and I", "author": ["Julia Quinn"], "length": "Length: 12 hrs and 9 mins"},
{"title": "A Thousand Li: The First Step", "author": ["Tao Wong"], "length": "Length: 8 hrs and 27 mins"},
{"title": "He Who Fights with Monsters 10", "author": ["Shirtaloon", "Travis Deverell"], "length": "Length: 25 hrs and 18 mins"},
{"title": "The Girl of His Dreams", "author": ["Susan Mallery"], "length": "Length: 6 hrs and 47 mins"},
{"title": "Iron Flame", "author": ["Rebecca Yarros"], "length": "Length: 28 hrs and 16 mins"},
{"title": "Law of the Jungle #2", "author": ["Vasily Mahanenko", "Mikhail Yagupov - translator"], "length": "Length: 7 hrs and 54 mins"},
{"title": "Tower of Dawn", "author": ["Sarah J. Maas"], "length": "Length: 22 hrs and 39 mins"},
{"title": "Confident Leader!", "author": ["Dan Reiland"], "length": "Length: 7 hrs and 2 mins"},
{"title": "The Crown of Gilded Bones", "author": ["Jennifer L. Armentrout"], "length": "Length: 25 hrs and 22 mins"},
{"title": "The Fellowship of the Ring", "author": ["J. R. R. Tolkien"], "length": "Length: 19 hrs and 7 mins"},
{"title": "Wild Love", "author": ["Elsie Silver"], "length": "Length: 11 hrs and 26 mins"},
{"title": "Harry Potter and the Chamber of Secrets, Book 2", "author": ["J.K. Rowling"], "length": "Length: 9 hrs and 2 mins"},
{"title": "Harry Potter and the Half-Blood Prince, Book 6", "author": ["J.K. Rowling"], "length": "Length: 18 hrs and 32 mins"},
{"title": "The Demonic Reflection", "author": ["Jessica Thibodeau"], "length": "Length: 6 hrs and 21 mins"},
{"title": "Light Bringer", "author": ["Pierce Brown"], "length": "Length: 30 hrs and 8 mins"},
{"title": "Becoming Supernatural", "author": ["Joe Dispenza"], "length": "Length: 14 hrs and 6 mins"},
{"title": "Fourth Wing (Part 2 of 2) (Dramatized Adaptation)", "author": ["Rebecca Yarros"], "length": "Length: 9 hrs and 22 mins"},
{"title": "The Two Towers", "author": ["J. R. R. Tolkien"], "length": "Length: 20 hrs and 46 mins"},
{"title": "Click Here to Kill Everybody", "author": ["Bruce Schneier"], "length": "Length: 8 hrs and 6 mins"},
{"title": "Honey Cut", "author": ["Sierra Simone"], "length": "Length: 13 hrs and 26 mins"},
{"title": "People We Meet on Vacation", "author": ["Emily Henry"], "length": "Length: 10 hrs and 46 mins"},
{"title": "The Two Towers", "author": ["J. R. R. Tolkien"], "length": "Length: 16 hrs and 40 mins"},
{"title": "The Devil's Hand", "author": ["Jack Carr"], "length": "Length: 14 hrs and 37 mins"},
{"title": "Think Faster, Talk Smarter", "author": ["Matt Abrahams"], "length": "Length: 7 hrs and 11 mins"},
{"title": "Promise of Vipers", "author": ["Steve McHugh"], "length": "Length: 11 hrs and 28 mins"},
{"title": "Trust Her", "author": ["Flynn Berry"], "length": "Length: 8 hrs and 45 mins"},
{"title": "He Who Fights with Monsters 4", "author": ["Shirtaloon", "Travis Deverell"], "length": "Length: 22 hrs and 20 mins"},
{"title": "Learn Conversational Italian for Beginners: 2 Books in 1", "author": ["Emily Montgomery"], "length": "Length: 20 hrs and 7 mins"},
{"title": "Recon", "author": ["Craig Alanson"], "length": "Length: 16 hrs and 26 mins"},
{"title": "Become a Studying and Learning Machine", "author": ["Peter Hollins"], "length": "Length: 3 hrs and 51 mins"},
{"title": "To Be Fated", "author": ["Willow Winters"], "length": "Length: 14 hrs and 42 mins"},
{"title": "The Coldest Case: The Past Has a Long Memory", "author": ["James Patterson", "Aaron Tracy", "Ryan Silbert"], "length": "Length: 3 hrs and 41 mins"},
{"title": "Fae and Fare", "author": ["pirateaba"], "length": "Length: 61 hrs and 4 mins"},
{"title": "The Lost Book of Medical Remedies", "author": ["Natalia Williams"], "length": "Length: 3 hrs and 10 mins"},
{"title": "24690", "author": ["A. A. Dark", "Alaska Angelini"], "length": "Length: 10 hrs and 2 mins"},
{"title": "A Court of Silver Flames (2 of 2) (Dramatized Adaptation)", "author": ["Sarah J. Maas"], "length": "Length: 10 hrs and 33 mins"},
{"title": "The Entrepreneurial Brain", "author": ["Jeff Hays"], "length": "Length: 7 hrs and 1 min"},
{"title": "Harry Potter and the Prisoner of Azkaban, Book 3", "author": ["J.K. Rowling"], "length": "Length: 11 hrs and 49 mins"},
{"title": "The Dark Forest", "author": ["Cixin Liu", "Joel Martinsen - translator"], "length": "Length: 22 hrs and 36 mins"},
{"title": "Romancing Mister Bridgerton", "author": ["Julia Quinn"], "length": "Length: 13 hrs and 17 mins"},
{"title": "Knot Again", "author": ["Lucy Scott Bryan"], "length": "Length: 17 hrs and 40 mins"},
{"title": "Eruption", "author": ["Michael Crichton", "James Patterson"], "length": "Length: 10 hrs and 32 mins"},
{"title": "The Groom List", "author": ["Ella Quinn"], "length": "Length: 9 hrs and 20 mins"},
{"title": "The Girl Who Remembers", "author": ["A.J. Rivers"], "length": "Length: 6 hrs and 55 mins"},
{"title": "The Girl Who Was Taken", "author": ["Charlie Donlea"], "length": "Length: 10 hrs and 49 mins"},
{"title": "The Rise and Fall of the Third Reich", "author": ["William L. Shirer"], "length": "Length: 57 hrs and 11 mins"},
{"title": "A Dance with Dragons", "author": ["George R.R. Martin"], "length": "Length: 48 hrs and 55 mins"},
{"title": "Heaven's River", "author": ["Dennis E. Taylor"], "length": "Length: 16 hrs and 57 mins"},
{"title": "The Power of Your Subconscious Mind Features Bonus Book: How to Attract Money (Deluxe Original Classic Edition)", "author": ["Dr. Joseph Murphy", "Mitch Horowitz"], "length": "Length: 11 hrs and 20 mins"},
{"title": "All My Secrets", "author": ["Lynn Austin"], "length": "Length: 12 hrs and 37 mins"},
{"title": "Wrathful Mortals", "author": ["Caroline Peckham", "Susanne Valenti"], "length": "Length: 11 hrs and 13 mins"},
{"title": "The Return of the King", "author": ["J. R. R. Tolkien"], "length": "Length: 21 hrs and 52 mins"},
{"title": "Impossible to Ignore", "author": ["Carmen Simon"], "length": "Length: 8 hrs and 28 mins"},
{"title": "Swan Song", "author": ["Elin Hilderbrand"], "length": "Length: 13 hrs and 39 mins"},
{"title": "Between the Lies", "author": ["L.T. Ryan", "K.M. Rought"], "length": "Length: 8 hrs and 16 mins"},
{"title": "The Forsaken", "author": ["Christopher G. Nuttall"], "length": "Length: 12 hrs and 33 mins"},
{"title": "Harry Potter and the Order of the Phoenix, Book 5", "author": ["J.K. Rowling"], "length": "Length: 26 hrs and 28 mins"},
{"title": "Harry Potter and the Deathly Hallows, Book 7", "author": ["J.K. Rowling"], "length": "Length: 21 hrs and 36 mins"},
{"title": "You Never Know", "author": ["Tom Selleck", "Ellis Henican"], "length": "Length: 12 hrs and 47 mins"},
{"title": "Torrent Witches Cozy Mysteries Complete Box Set: Books 1-10", "author": ["Tess Lake"], "length": "Length: 65 hrs and 31 mins"},
{"title": "Not in Love", "author": ["Ali Hazelwood"], "length": "Length: 11 hrs and 55 mins"},
{"title": "The David Wolf Mystery Thriller Series: Books 1-4", "author": ["Jeff Carson"], "length": "Length: 28 hrs and 16 mins"},
{"title": "The Path of Ascension: Books 1-3.5", "author": ["C. Mantis"], "length": "Length: 70 hrs and 2 mins"},
{"title": "Countdown", "author": ["Sean Oswald"], "length": "Length: 13 hrs and 13 mins"},
{"title": "Chrysalis, Books 1-3", "author": ["RinoZ"], "length": "Length: 54 hrs and 41 mins"},
{"title": "Iron Flame (Part 1 of 2) (Dramatized Adaptation)", "author": ["Rebecca Yarros"], "length": "Length: 11 hrs and 38 mins"},
{"title": "Alpha Dragon's Ferret", "author": ["Hawke Oakley"], "length": "Length: 8 hrs and 12 mins"},
{"title": "When He Was Wicked", "author": ["Julia Quinn"], "length": "Length: 11 hrs and 29 mins"},
{"title": "Heavenly Chaos", "author": ["Daniel Schinhofen"], "length": "Length: 11 hrs and 56 mins"},
{"title": "A Different Drummer", "author": ["William Melvin Kelley"], "length": "Length: 6 hrs and 35 mins"},
{"title": "Code of Arms", "author": ["Jack Slater"], "length": "Length: 12 hrs and 29 mins"},
{"title": "Frigid Magic", "author": ["Bruce Sentar"], "length": "Length: 15 hrs and 24 mins"},
{"title": "The Last Survivors Box Set", "author": ["Bobby Adair", "T.W. Piperbrook"], "length": "Length: 50 hrs and 24 mins"},
{"title": "Leather & Lark", "author": ["Brynne Weaver"], "length": "Length: 12 hrs and 15 mins"},
{"title": "Amazon Apocalypse 2", "author": ["Marvin Knight"], "length": "Length: 25 hrs and 35 mins"},
{"title": "Red Man", "author": ["Richard Fox"], "length": "Length: 8 hrs and 11 mins"},
{"title": "The Five Year Lie", "author": ["Sarina Bowen"], "length": "Length: 12 hrs and 41 mins"},
{"title": "Days of Want Series, Books 1-7", "author": ["T. L. Payne"], "length": "Length: 43 hrs and 42 mins"},
{"title": "Winter Lost", "author": ["Patricia Briggs"], "length": "Length: 11 hrs and 15 mins"},
{"title": "Mad Love", "author": ["Wendy Walker"], "length": "Length: 4 hrs and 11 mins"},
{"title": "The Eye of the Bedlam Bride", "author": ["Matt Dinniman"], "length": "Length: 26 hrs and 46 mins"},
{"title": "Othered", "author": ["Jenai Auman"], "length": "Length: 7 hrs and 9 mins"},
{"title": "How to Find a Princess", "author": ["Alyssa Cole"], "length": "Length: 10 hrs and 48 mins"},
{"title": "Death Watch", "author": ["Mike Ryan"], "length": "Length: 5 hrs and 22 mins"},
{"title": "Best Seat in the House", "author": ["Jack Nicklaus II", "Don Yaeger", "Jack Nicklaus - foreword"], "length": "Length: 5 hrs and 28 mins"},
{"title": "A Queen This Fierce and Deadly", "author": ["Stacia Stark"], "length": "Length: 17 hrs and 19 mins"},
{"title": "The Mermaid's Daughter", "author": ["Ann Claycomb"], "length": "Length: 12 hrs and 50 mins"},
{"title": "Hell Divers III: Deliverance", "author": ["Nicholas Sansbury Smith"], "length": "Length: 11 hrs and 18 mins"},
{"title": "Caught on Camera", "author": ["Chelsea Curto"], "length": "Length: 18 hrs and 3 mins"},
{"title": "Outlive", "author": ["Peter Attia MD", "Bill Gifford - contributor"], "length": "Length: 17 hrs and 7 mins"},
{"title": "Jack Zulu and the Girl with Golden Wings", "author": ["S. D. Smith", "J. C. Smith"], "length": "Length: 7 hrs and 54 mins"},
{"title": "A Lark's Conceit", "author": ["Lynn Messina"], "length": "Length: 9 hrs and 51 mins"},
{"title": "The Bad Weather Friend", "author": ["Dean Koontz"], "length": "Length: 8 hrs and 42 mins"},
{"title": "This Is Why We Lied", "author": ["Karin Slaughter"], "length": "Length: 18 hrs and 6 mins"},
{"title": "Invading the System", "author": ["Inadvisably Compelled"], "length": "Length: 13 hrs and 27 mins"},
{"title": "Twisted Lies", "author": ["Ana Huang"], "length": "Length: 16 hrs and 23 mins"},
{"title": "Rich Dad Poor Dad: 20th Anniversary Edition", "author": ["Robert T. Kiyosaki"], "length": "Length: 8 hrs and 22 mins"},
{"title": "The Gate of the Feral Gods", "author": ["Matt Dinniman"], "length": "Length: 18 hrs and 3 mins"},
{"title": "Hábitos atómicos (Español neutro)", "author": ["James Clear"], "length": "Length: 9 hrs and 1 min"},
{"title": "Bare", "author": ["Raina O'Dell"], "length": "Length: 10 hrs and 7 mins"},
{"title": "A Gentleman and a Thief", "author": ["Dean Jobb"], "length": "Length: 10 hrs and 46 mins"},
{"title": "The Housemaid Is Watching", "author": ["Freida McFadden"], "length": "Length: 11 hrs and 42 mins"},
{"title": "Lovecraft's Monsters", "author": ["Neil Gaiman", "Ellen Datlow - editor"], "length": "Length: 15 hrs and 12 mins"},
{"title": "Brain Hacks", "author": ["Lara Honos-Webb PhD"], "length": "Length: 4 hrs and 8 mins"},
{"title": "Speak with Impact", "author": ["Allison Shapira"], "length": "Length: 6 hrs and 12 mins"},
{"title": "Waiting Isn't a Waste", "author": ["Mark Vroegop", "Jen Wilkin - foreword"], "length": "Length: 2 hrs and 57 mins"},
{"title": "The Fellowship of the Ring", "author": ["J. R. R. Tolkien"], "length": "Length: 22 hrs and 38 mins"},
{"title": "To Sir Phillip, with Love", "author": ["Julia Quinn"], "length": "Length: 11 hrs and 10 mins"},
{"title": "It Starts with Us", "author": ["Colleen Hoover"], "length": "Length: 8 hrs and 41 mins"},
{"title": "Meditations for Ancestral Healing, Guidance & Veneration", "author": ["Abiola Abrams"], "length": "Length: 1 hr and 43 mins"},
{"title": "Prototype", "author": ["Jez Cajiao"], "length": "Length: 21 hrs and 25 mins"},
{"title": "The Butcher's Masquerade", "author": ["Matt Dinniman"], "length": "Length: 23 hrs and 33 mins"},
{"title": "Apostle", "author": ["Tom Bissell"], "length": "Length: 14 hrs and 17 mins"},
{"title": "How to Talk to Anyone", "author": ["Leil Lowndes"], "length": "Length: 8 hrs and 59 mins"},
{"title": "He Who Fights with Monsters 2", "author": ["Shirtaloon", "Travis Deverell"], "length": "Length: 22 hrs and 1 min"},
{"title": "Not Till We Are Lost", "author": ["Dennis E. Taylor"], "length": "Length: 11 hrs and 41 mins"},
{"title": "Only Daughter: A gripping and emotional psychological thriller with a jaw-dropping twist", "author": ["Sarah A. Denzil"], "length": "Length: 11 hrs and 11 mins"},
{"title": "Red Rising", "author": ["Pierce Brown"], "length": "Length: 16 hrs and 12 mins"},
{"title": "AI Prosperity Blueprint", "author": ["Julio D. Velez"], "length": "Length: 3 hrs and 37 mins"},
{"title": "[CD10]本好きの下剋上～司書になるためには手段を選んでいられません～ドラマCD10", "author": ["香月 美夜"], "length": "Length: 2 hrs and 13 mins"},
{"title": "Huge Games", "author": ["Stephanie Brother"], "length": "Length: 8 hrs and 27 mins"},
{"title": "Corruption Wielder", "author": ["Aaron Shih"], "length": "Length: 17 hrs and 4 mins"},
{"title": "Exodus", "author": ["Kate Stewart"], "length": "Length: 14 hrs and 24 mins"},
{"title": "Darkoath", "author": ["Chris Thursten"], "length": "Length: 10 hrs and 35 mins"},
{"title": "Jake's Magical Market 3", "author": ["J.R. Mathews"], "length": "Length: 36 hrs and 21 mins"},
{"title": "To Charm a Lady", "author": ["Joanna Barker"], "length": "Length: 9 hrs and 44 mins"},
{"title": "Don't Let Me Go", "author": ["Catherine Ryan Hyde"], "length": "Length: 11 hrs and 17 mins"},
{"title": "Long Division", "author": ["Kiese Laymon"], "length": "Length: 8 hrs and 10 mins"},
{"title": "Harry Potter and the Half-Blood Prince (Narrated by Stephen Fry)", "author": ["J.K. Rowling"], "length": "Length: 20 hrs and 31 mins"},
{"title": "Save Me", "author": ["Sharon Sala", "K.D. Richards"], "length": "Length: 11 hrs and 18 mins"},
{"title": "Heartbreaker Handoff", "author": ["Lex Martin"], "length": "Length: 9 hrs and 26 mins"},
{"title": "House of Flame and Shadow", "author": ["Sarah J. Maas"], "length": "Length: 29 hrs and 42 mins"}
]